mcp_repl/__init__.py
mcp_repl/llm_client.py
mcp_repl/mcp_orchestrator.py
mcp_repl/repl.py
mcp_repl-0.1.3.dist-info/METADATA
mcp_repl-0.1.3.dist-info/WHEEL
mcp_repl-0.1.3.dist-info/entry_points.txt
mcp_repl-0.1.3.dist-info/licenses/LICENSE
mcp_repl-0.1.3.dist-info/RECORD
