Metadata-Version: 2.4
Name: mcp-repl
Version: 0.1.3
Summary: Add your description here
Author-email: truskovskiyk <truskovskiyk@gmail.com>
License-File: LICENSE
Requires-Python: >=3.12
Requires-Dist: aiohttp>=3.11.13
Requires-Dist: anthropic>=0.49.0
Requires-Dist: mcp[cli]>=1.3.0
Requires-Dist: openai>=1.65.5
Requires-Dist: prompt-toolkit>=3.0.50
Requires-Dist: python-dotenv>=1.0.1
Requires-Dist: ruff>=0.9.9
Provides-Extra: databases
Requires-Dist: faker>=36.2.2; extra == 'databases'
Requires-Dist: mysql-connector-python>=9.2.0; extra == 'databases'
Requires-Dist: psycopg2-binary>=2.9.10; extra == 'databases'
Requires-Dist: redis>=5.2.1; extra == 'databases'
Provides-Extra: infra
Requires-Dist: kubernetes>=32.0.1; extra == 'infra'
Requires-Dist: modal>=0.73.106; extra == 'infra'
Provides-Extra: test
Requires-Dist: pytest-asyncio>=0.25.3; extra == 'test'
Requires-Dist: pytest>=7.4.0; extra == 'test'
